huge.py
huge-0.1.3.dist-info/entry_points.txt
huge-0.1.3.dist-info/LICENSE
huge-0.1.3.dist-info/WHEEL
huge-0.1.3.dist-info/METADATA
huge-0.1.3.dist-info/RECORD
