Metadata-Version: 2.1
Name: huge
Version: 0.1.3
Summary: Find huge additions in Git history.
Home-page: https://github.com/bast/huge
Author: Radovan Bast
Author-email: radovan.bast@uit.no
Classifier: License :: OSI Approved :: MIT License
Requires-Dist: tqdm>=4.65,<5
Requires-Dist: click>=8.1,<9
Requires-Dist: tabulate>=0.9,<0.10
